sxlogic/__init__.py
sxlogic/__main__.py
sxlogic/fpgacap.py
sxlogic/iconvert.py
sxlogic/monocle.py
sxlogic/sxlogic.py
sxlogic-0.4.3.dist-info/METADATA
sxlogic-0.4.3.dist-info/WHEEL
sxlogic-0.4.3.dist-info/entry_points.txt
sxlogic-0.4.3.dist-info/top_level.txt
sxlogic-0.4.3.dist-info/RECORD
